gitbuglink/__init__.py
gitbuglink/gitbuglink.py
gitbuglink-0.0.2.dist-info/WHEEL
gitbuglink-0.0.2.dist-info/metadata.json
gitbuglink-0.0.2.dist-info/top_level.txt
gitbuglink-0.0.2.dist-info/entry_points.txt
gitbuglink-0.0.2.dist-info/RECORD
gitbuglink-0.0.2.dist-info/DESCRIPTION.rst
gitbuglink-0.0.2.dist-info/METADATA
