Metadata-Version: 2.0
Name: gitbuglink
Version: 0.0.2
Summary: The stupid commit-bug traceability linker for the stupid content tracker
Home-page: https://github.com/cscorley/gitbuglink
Author: Christopher S. Corley
Author-email: cscorley@crimson.ua.edu
License: The MIT License (MIT)
Requires-Dist: dulwich
Requires-Dist: click
